{
  "type": "MaxHistoryTrackerFeaturizer",
  "state_featurizer": {
    "action_texts": [],
    "entity_tag_specs": [],
    "feature_states": {
      "intent": {
        "ask_contact_info": 0,
        "ask_disease_cause": 1,
        "ask_disease_symptoms": 2,
        "ask_disease_what": 3,
        "ask_learning_resources": 4,
        "ask_selfcare_diet": 5,
        "ask_selfcare_emotion": 6,
        "ask_selfcare_rest": 7,
        "ask_treatment_chemo_what": 8,
        "ask_treatment_dos_donts": 9,
        "ask_treatment_side_effects": 10,
        "back": 11,
        "goodbye": 12,
        "greet": 13,
        "nlu_fallback": 14,
        "out_of_scope": 15,
        "restart": 16,
        "session_start": 17,
        "show_menu": 18,
        "show_menu_disease": 19,
        "show_menu_faq": 20,
        "show_menu_selfcare": 21,
        "show_menu_treatment": 22,
        "thank": 23
      },
      "action_name": {
        "action_listen": 0,
        "action_restart": 1,
        "action_session_start": 2,
        "action_default_fallback": 3,
        "action_deactivate_loop": 4,
        "action_revert_fallback_events": 5,
        "action_default_ask_affirmation": 6,
        "action_default_ask_rephrase": 7,
        "action_two_stage_fallback": 8,
        "action_unlikely_intent": 9,
        "action_back": 10,
        "...": 11,
        "action_extract_slots": 12,
        "action_get_answer": 13,
        "action_send_main_menu": 14,
        "action_send_disease_menu": 15,
        "action_send_treatment_menu": 16,
        "action_send_selfcare_menu": 17,
        "action_get_learning_resources": 18,
        "action_send_faq_menu": 19,
        "utter_goodbye": 20,
        "utter_greet": 21,
        "utter_out_of_scope": 22,
        "utter_thank": 23
      },
      "entities": {},
      "slots": {},
      "active_loop": {}
    }
  },
  "remove_duplicates": true,
  "max_history": 5
}